pywos/__init__.py
pywos/analysis.py
pywos/cons.py
pywos/crawler.py
pywos-0.0.1.dist-info/DESCRIPTION.rst
pywos-0.0.1.dist-info/METADATA
pywos-0.0.1.dist-info/RECORD
pywos-0.0.1.dist-info/WHEEL
pywos-0.0.1.dist-info/metadata.json
pywos-0.0.1.dist-info/top_level.txt
