Metadata-Version: 2.0
Name: pywos
Version: 0.0.1
Summary: Citation data export and analysis from web of science
Home-page: https://github.com/refraction-ray/wos-statistics
Author: refraction-ray
Author-email: refraction-ray@protonmail.com
License: UNKNOWN
Platform: UNKNOWN
Classifier: Programming Language :: Python :: 3
Classifier: License :: OSI Approved :: MIT License
Classifier: Operating System :: OS Independent
Requires-Dist: aiohttp (>=3.4)
Requires-Dist: pandas
Requires-Dist: beautifulsoup4
